hello_tea.py
ceceliama_tea.xyz-1.0.6.dist-info/METADATA
ceceliama_tea.xyz-1.0.6.dist-info/WHEEL
ceceliama_tea.xyz-1.0.6.dist-info/entry_points.txt
ceceliama_tea.xyz-1.0.6.dist-info/top_level.txt
ceceliama_tea.xyz-1.0.6.dist-info/RECORD
